LICENSE
README.md
setup.py
pycafe24/__init__.py
pycafe24/cache.py
pycafe24/exceptions.py
pycafe24/functions.py
pycafe24/oauth2.py
pycafe24.egg-info/PKG-INFO
pycafe24.egg-info/SOURCES.txt
pycafe24.egg-info/dependency_links.txt
pycafe24.egg-info/requires.txt
pycafe24.egg-info/top_level.txt