Metadata-Version: 2.1
Name: pycafe24
Version: 1.3
Summary: A Cafe24 API library
Author: Sung Jun Hong
Author-email: sjtheorange@gmail.com
License-File: LICENSE
